LICENSE
README.md
setup.py
simcap/__init__.py
simcap/base.py
simcap/exceptions.py
simcap/finance.py
simcap/markov.py
simcap.egg-info/PKG-INFO
simcap.egg-info/SOURCES.txt
simcap.egg-info/dependency_links.txt
simcap.egg-info/requires.txt
simcap.egg-info/top_level.txt
simcap/datasets/__init__.py
simcap/datasets/csv/__init__.py
simcap/datasets/csv/asset_price_history.csv
simcap/datasets/csv/external_factors.csv
simcap/datasets/csv/proto_US_large_cap.csv
simcap/datasets/csv/proto_US_mid_cap.csv
simcap/datasets/csv/proto_US_small_cap.csv
simcap/datasets/csv/proto_emerging_markets.csv
simcap/datasets/csv/proto_foreign_developed.csv
simcap/datasets/csv/proto_global_bond.csv
simcap/datasets/csv/proto_real_estate.csv
simcap/datasets/csv/proto_total_bond.csv
tests/test_base.py