Metadata-Version: 2.2
Name: simcap
Version: 0.2.1
Summary: Simulation of Correlated Asset Prices
Home-page: https://github.com/jeremy-doyle/simcap
Author: Jeremy Doyle
Author-email: hello@jeremy-doyle.com
License: MIT
Keywords: finance,investment,analysis,securities,simulation,markov,time,series,monte,carlo,risk
Classifier: Development Status :: 3 - Alpha
Classifier: Programming Language :: Python :: 3.7
Classifier: Programming Language :: Python :: 3.8
Classifier: Programming Language :: Python :: 3.9
Classifier: Programming Language :: Python :: 3.10
Classifier: Programming Language :: Python :: 3.11
Classifier: Programming Language :: Python :: 3.12
Classifier: Programming Language :: Python :: 3.13
Classifier: Operating System :: OS Independent
Classifier: License :: OSI Approved :: MIT License
Classifier: Intended Audience :: Developers
Classifier: Intended Audience :: Financial and Insurance Industry
Classifier: Intended Audience :: Science/Research
Classifier: Topic :: Office/Business :: Financial
Classifier: Topic :: Office/Business :: Financial :: Investment
Classifier: Topic :: Scientific/Engineering :: Information Analysis
Requires-Python: >=3.7
License-File: LICENSE
Requires-Dist: numpy>=1.17
Requires-Dist: scipy>=1.9.0
Requires-Dist: statsmodels>=0.13.0
Requires-Dist: scikit-learn>=0.18
Requires-Dist: hmmlearn>=0.2.7
Requires-Dist: pandas>=1.0
Requires-Dist: tqdm
Dynamic: author
Dynamic: author-email
Dynamic: classifier
Dynamic: description
Dynamic: description-content-type
Dynamic: home-page
Dynamic: keywords
Dynamic: license
Dynamic: requires-dist
Dynamic: requires-python
Dynamic: summary
